PyCosmo/Background.py
PyCosmo/Cosmo.py
PyCosmo/CosmologyCore.py
PyCosmo/CosmologyCore_massivenu.py
PyCosmo/CosmologyCore_massivenu_rsa.py
PyCosmo/CosmologyCore_massivenu_wcdm.py
PyCosmo/CosmologyCore_massivenu_wcdm_rsa.py
PyCosmo/CosmologyCore_rsa.py
PyCosmo/CosmologyCore_wcdm.py
PyCosmo/CosmologyCore_wcdm_rsa.py
PyCosmo/LinearPerturbationApprox.py
PyCosmo/LinearPerturbationBase.py
PyCosmo/NonLinearPerturbationHaloFit.py
PyCosmo/NonLinearPerturbationMead.py
PyCosmo/NonLinearPerturbation_HI.py
PyCosmo/NonLinearPerturbation_HaloModel.py
PyCosmo/Obs.py
PyCosmo/PerturbationBase.py
PyCosmo/PerturbationTable.py
PyCosmo/Projection.py
PyCosmo/TheoryPredTables.py
PyCosmo/_Cosmics.py
PyCosmo/_Recombination.py
PyCosmo/_RecombinationClass.py
PyCosmo/_RecombinationCosmics.py
PyCosmo/_Util.py
PyCosmo/__init__.py
PyCosmo/_scipy_utils.py
PyCosmo/build.py
PyCosmo/core_file_handling.py
PyCosmo/disable_multithreading.py
PyCosmo/ini_handling.py
PyCosmo/model_config.py
PyCosmo/optimize_nq.py
PyCosmo/patches.py
PyCosmo/predefined_k_grids.py
PyCosmo/BoltzmannSolver/Fields.py
PyCosmo/BoltzmannSolver/LinearPerturbationBoltzmann.py
PyCosmo/BoltzmannSolver/LsodaSolver.py
PyCosmo/BoltzmannSolver/ScipySolver.py
PyCosmo/BoltzmannSolver/__init__.py
PyCosmo/config/__init__.py
PyCosmo/config/default_lcdm.ini
PyCosmo/config/default_lcdm_rsa.ini
PyCosmo/config/default_mnulcdm.ini
PyCosmo/config/default_mnulcdm_rsa.ini
PyCosmo/config/default_mnuwcdm.ini
PyCosmo/config/default_mnuwcdm_rsa.ini
PyCosmo/config/default_wcdm.ini
PyCosmo/config/default_wcdm_rsa.ini
PyCosmo/config/load_parameters_ini.py
PyCosmo/cython/__init__.py
PyCosmo/cython/const.c
PyCosmo/cython/constf.c
PyCosmo/cython/halo_integral.c
PyCosmo/cython/halo_integral.cpython-312-darwin.so
PyCosmo/cython/halo_integral.pyx
PyCosmo/cython/halo_integral_1h.c
PyCosmo/cython/halo_integral_1h.cpython-312-darwin.so
PyCosmo/cython/halo_integral_1h.pyx
PyCosmo/cython/halo_integral_2h.c
PyCosmo/cython/halo_integral_2h.cpython-312-darwin.so
pycosmo-2.2.2.dist-info/licenses/AUTHORS.rst
pycosmo-2.2.2.dist-info/licenses/LICENSE
pycosmo-2.2.2.dist-info/METADATA
pycosmo-2.2.2.dist-info/WHEEL
pycosmo-2.2.2.dist-info/entry_points.txt
pycosmo-2.2.2.dist-info/top_level.txt
pycosmo-2.2.2.dist-info/RECORD
